geoffrey_todo-0.0.2.dist-info/DESCRIPTION.rst
geoffrey_todo-0.0.2.dist-info/RECORD
geoffrey_todo-0.0.2.dist-info/WHEEL
geoffrey_todo-0.0.2.dist-info/top_level.txt
geoffrey_todo-0.0.2.dist-info/metadata.json
geoffrey_todo-0.0.2.dist-info/METADATA
geoffreyplugins/todo.py
geoffreyplugins/__init__.py
geoffreyplugins/todo/main.js
geoffreyplugins/todo/assets/widget.html
geoffreyplugins/todo/assets/.gitkeep
