Metadata-Version: 2.0
Name: geoffrey-todo
Version: 0.0.2
Summary: Collects all TODO notes in source files.
Home-page: https://github.com/nilp0inter/geoffrey-todo
Author: Roberto Abdelkader Martínez Pérez
Author-email: robertomartinezp@gmail.com
License: UNKNOWN
Platform: UNKNOWN
